{"sections":{"main":{"type":"companion-banner","settings":{"nora_logo":"shopify:\/\/shop_images\/Smart_Nora_Logo_White_4179019c-7641-476b-9ecf-89e1a065d7c6.svg","heading":"Don’t just track your sleep, transform it","button_label":"","content":"Click on the link below on your phone to download the app.<span> <\/span>","apple_store_image":"shopify:\/\/shop_images\/App_Store_Badge.svg","apple_store_link":"https:\/\/apps.apple.com\/ca\/app\/smart-nora\/id6739359711","google_play_image":"shopify:\/\/shop_images\/Pre-Order_on_Google_Play.svg","google_play_link":"https:\/\/play.google.com\/store\/apps\/details?id=com.mycompany.noraapp&pcampaignid=web_share","image":"shopify:\/\/shop_images\/Gen_2_with_Phone_8f9b2cec-c9c6-4769-89c2-543378712ecd.webp"}},"companion_fetaures_fQwrbt":{"type":"companion-fetaures","blocks":{"feature_WpBj84":{"type":"feature","settings":{"mobile_image":"shopify:\/\/shop_images\/Data_Rich.webp","title":"Track snoring","content":"Track your snoring with Smart Nora Pebble or with the mobile app."}},"feature_qyxeNf":{"type":"feature","settings":{"mobile_image":"shopify:\/\/shop_images\/weekly.webp","title":"See improvements","content":"Get a detailed picture of your snoring improvement."}},"feature_N9PRKN":{"type":"feature","settings":{"mobile_image":"shopify:\/\/shop_images\/OnCallHelp.webp","title":"Get on-call support","content":"Talk to Smart Nora customer support directly through the app."}}},"block_order":["feature_WpBj84","feature_qyxeNf","feature_N9PRKN"],"settings":{"heading":"Features"}},"companion_cta_wkPanU":{"type":"companion-cta","settings":{"heading":"Need help setting up your Gen2 device?","content":"Check out our helpful documentation or contact our customer experience team","button_label":"Chat now!","button_link":"#","button_label_1":"Setup docs","button_link_1":"https:\/\/support.smartnora.com\/portal\/en\/kb\/articles\/how-do-i-set-up-my-nora","image":"shopify:\/\/shop_images\/Gen_2_Pebble.webp"}},"companion_roadmap_eFbXNF":{"type":"companion-roadmap","blocks":{"phase_GKmFzw":{"type":"phase","settings":{"image":"shopify:\/\/shop_images\/Completed.svg","is_content_bold":false,"pre_title":"completed","title":"Development"}},"phase_YiYLGx":{"type":"phase","settings":{"image":"shopify:\/\/shop_images\/We_are_here.svg","is_content_bold":true,"pre_title":"we are here","title":"iOS app\nBeta Testing"}},"phase_wAcpBy":{"type":"phase","settings":{"image":"shopify:\/\/shop_images\/IOS_Release.svg","is_content_bold":false,"pre_title":"February, 2025","title":"iOS app \nRelease"}},"phase_Lbx4fF":{"type":"phase","settings":{"image":"shopify:\/\/shop_images\/Status.svg","is_content_bold":false,"pre_title":"February, 2025","title":"Android\nBeta Testing"}},"phase_QtLKNw":{"type":"phase","settings":{"image":"shopify:\/\/shop_images\/Android_Testing_2246abf0-1bc6-463f-bf85-054e613acd73.svg","is_content_bold":false,"pre_title":"TBD","title":"Android\nRelease"}}},"block_order":["phase_GKmFzw","phase_YiYLGx","phase_wAcpBy","phase_Lbx4fF","phase_QtLKNw"],"disabled":true,"settings":{"heading":"Our Roadmap","content":"Our mobile app will continue to evolve to bring you more of what you need to understand your sleep, get a good night’s rest and wake up refreshed."}},"companion_talk_to_us_x8fk4P":{"type":"companion-talk-to-us","settings":{"title":"Talk to us any time","content":"Our customer experience team is on call to answer any questions or help you set up your Smart Nora\n<br><br>\nEmail: <a href=\"mailto:Support@smartnora.com\">Support@smartnora.com<\/a>","button_1_icon":"shopify:\/\/shop_images\/Vector_f150733f-12c1-4143-b283-0632a116edac.svg","button_2_icon":"shopify:\/\/shop_images\/Vector_1_8f65b2b7-196c-4523-adbd-705f3549f2b2.svg","button_1_label":"","button_1_link":"","button_2_label":"Chat now!","button_2_link":""}}},"order":["main","companion_fetaures_fQwrbt","companion_cta_wkPanU","companion_roadmap_eFbXNF","companion_talk_to_us_x8fk4P"]}